README.md
pyproject.toml
src/ca_certificates/__init__.py
src/vishal_t_core_web_sm.egg-info/PKG-INFO
src/vishal_t_core_web_sm.egg-info/SOURCES.txt
src/vishal_t_core_web_sm.egg-info/dependency_links.txt
src/vishal_t_core_web_sm.egg-info/top_level.txt