Metadata-Version: 2.4
Name: vishal-t-core-web-sm
Version: 0.0.0
Summary: Dummy vishal-t-core-web-sm package for PyPI
Author-email: Your Name <you@example.com>
Requires-Python: >=3.7
